requirements.txt
setup.py
requests_api_pagination/__init__.py
requests_api_pagination.egg-info/PKG-INFO
requests_api_pagination.egg-info/SOURCES.txt
requests_api_pagination.egg-info/dependency_links.txt
requests_api_pagination.egg-info/requires.txt
requests_api_pagination.egg-info/top_level.txt