Metadata-Version: 2.1
Name: requests-api-pagination
Version: 2020.7.1
Summary: requests rfc5988 api pagination
Home-page: https://github.com/andrewp-as-is/requests-api-pagination.py
License: Unlicense
Keywords: requests rfc5988 api pagination
Platform: UNKNOWN
Classifier: License :: Public Domain
Classifier: Operating System :: OS Independent
Classifier: Programming Language :: Python :: 3
